corpas/1.py
corpas/2.py
corpas/3.py
corpas/4.py
corpas/5.py
corpas/6.py
corpas/7.py
corpas/8.py
corpas/9.py
corpas/__init__.py
corpas/code_printer.py
nlkt-4.0.1.dist-info/METADATA
nlkt-4.0.1.dist-info/WHEEL
nlkt-4.0.1.dist-info/top_level.txt
nlkt-4.0.1.dist-info/RECORD
