Metadata-Version: 2.4
Name: nlkt
Version: 4.0.1
Summary: A short description of your package
Author: CrypticX
Author-email: your.email@example.com
Classifier: Programming Language :: Python :: 3
Classifier: License :: OSI Approved :: MIT License
Classifier: Operating System :: OS Independent
Requires-Python: >=3.6
Requires-Dist: gensim==4.3.3
Requires-Dist: scipy==1.13.1
Requires-Dist: numpy==1.26.4
Requires-Dist: hmmlearn==0.3.3
Requires-Dist: keras==3.9.0
Requires-Dist: pandas==2.2.3
Requires-Dist: sklearn-crfsuite==0.5.0
Dynamic: author
Dynamic: author-email
Dynamic: classifier
Dynamic: requires-dist
Dynamic: requires-python
Dynamic: summary
